aiomatrix/__init__.py
aiomatrix/loggers.py
aiomatrix/client/__init__.py
aiomatrix/client/client.py
aiomatrix/client/apis/__init__.py
aiomatrix/client/apis/auth.py
aiomatrix/client/apis/capabilities_negotiation.py
aiomatrix/client/apis/listing_rooms.py
aiomatrix/client/apis/raw_api.py
aiomatrix/client/apis/room_membership.py
aiomatrix/client/apis/rooms.py
aiomatrix/client/apis/syncing.py
aiomatrix/client/apis/modules/__init__.py
aiomatrix/client/apis/modules/content_repository.py
aiomatrix/client/apis/modules/instant_messaging.py
aiomatrix/client/apis/modules/presence_api.py
aiomatrix/client/apis/modules/typing_notifications.py
aiomatrix/dispatcher/__init__.py
aiomatrix/dispatcher/dispatcher.py
aiomatrix/dispatcher/filters/__init__.py
aiomatrix/dispatcher/filters/base.py
aiomatrix/dispatcher/filters/builtin.py
aiomatrix/dispatcher/handlers/__init__.py
aiomatrix/dispatcher/handlers/handler.py
aiomatrix/dispatcher/observers/__init__.py
aiomatrix/dispatcher/observers/matrix.py
aiomatrix/dispatcher/storage/__init__.py
aiomatrix/dispatcher/storage/storage.py
aiomatrix/dispatcher/storage/base_engines/__init__.py
aiomatrix/dispatcher/storage/base_engines/sqlite.py
aiomatrix/dispatcher/storage/internal_data/__init__.py
aiomatrix/dispatcher/storage/internal_data/base.py
aiomatrix/dispatcher/storage/internal_data/repo.py
aiomatrix/dispatcher/storage/internal_data/sqlite.py
aiomatrix/dispatcher/storage/internal_data/engines/__init__.py
aiomatrix/dispatcher/storage/internal_data/engines/sqlite.py
aiomatrix/dispatcher/storage/internal_data/models/__init__.py
aiomatrix/dispatcher/storage/internal_data/models/internal_data_pair.py
aiomatrix/dispatcher/storage/presence/__init__.py
aiomatrix/dispatcher/storage/presence/base.py
aiomatrix/dispatcher/storage/presence/repo.py
aiomatrix/dispatcher/storage/presence/sqlite.py
aiomatrix/dispatcher/storage/presence/engines/__init__.py
aiomatrix/dispatcher/storage/presence/engines/sqlite.py
aiomatrix_py-0.4.7.dist-info/LICENSE.md
aiomatrix_py-0.4.7.dist-info/METADATA
aiomatrix_py-0.4.7.dist-info/WHEEL
aiomatrix_py-0.4.7.dist-info/top_level.txt
aiomatrix_py-0.4.7.dist-info/RECORD
